bvhtomimic.py
bvhtodeepmimic/__init__.py
bvhtodeepmimic/bvh_extended.py
bvhtodeepmimic/bvh_joint.py
bvhtodeepmimic/bvh_joint_handler.py
bvhtodeepmimic/joint_info.py
bvhtodeepmimic-0.0.1.dist-info/LICENSE.md
bvhtodeepmimic-0.0.1.dist-info/METADATA
bvhtodeepmimic-0.0.1.dist-info/WHEEL
bvhtodeepmimic-0.0.1.dist-info/top_level.txt
bvhtodeepmimic-0.0.1.dist-info/RECORD
