Metadata-Version: 2.1
Name: bvhtodeepmimic
Version: 0.0.1
Summary: Convert .bvh files (Biovision Hierarchy) to DeepMimic format.
Home-page: https://github.com/BartMoyaers/BvhToDeepMimic
Author: Bart Moyaers
Author-email: bart.moyaers@gmail.com
License: UNKNOWN
Platform: UNKNOWN
Classifier: Programming Language :: Python :: 3
Classifier: License :: OSI Approved :: MIT License
Classifier: Operating System :: OS Independent
Requires: pyquaternion
Requires: numpy
Requires: bvh
Requires: tqdm
